{"api__media_contributing.md":"CITLFv0T","api_array.md":"CPpP2rks","api_functions_debounce.md":"DgAttO17","api_functions_delay.md":"BRH-0APD","api_functions_index.md":"uDSE5MPe","api_functions_throttle.md":"Bnf_hy_i","api_globals.md":"CJbCoDQY","api_index.md":"Dztm1Rrn","api_object.md":"DPxPkAfY","api_readme.md":"DB4cvf_a","api_string.md":"CrTzU1ap","api_validation.md":"8-yZemVS","en_api__media_contributing.md":"FSYnpKeW","en_api_array.md":"BxgABcCD","en_api_functions_debounce.md":"CFQ8pTdA","en_api_functions_delay.md":"miwiq3U3","en_api_functions_index.md":"DpNHXwSX","en_api_functions_throttle.md":"DMzdGc8o","en_api_globals.md":"CCTLk19E","en_api_index.md":"C7sVpbaK","en_api_object.md":"BwjhM-NQ","en_api_readme.md":"8l7s0I70","en_api_string.md":"JOMLgEaL","en_api_validation.md":"igBZBYbW","en_guide_contributing.md":"xvofR7k3","en_guide_examples.md":"DFgu18Ge","en_guide_functions.md":"DaH_0cv7","en_guide_getting-started.md":"B15fdxAT","en_guide_index.md":"CNLSJR-s","en_guide_installation.md":"Dz7qjhAa","en_guide_performance.md":"D9WaCfoB","en_index.md":"CIZVP0XW","en_playground_index.md":"BpsiA0w-","guide_contributing.md":"C6ehnhjh","guide_examples.md":"BCw9XLim","guide_functions.md":"BvnVB8xJ","guide_getting-started.md":"DivbxnyY","guide_index.md":"DxEVqYFD","guide_installation.md":"BsHZ-m1u","guide_performance.md":"BiynIcaK","index.md":"BqX2bLdM","playground_index.md":"DaGZw2Ed"}
